projectstructor/__init__.py
projectstructor/detector.py
projectstructor-2025.5.180959.dist-info/licenses/LICENSE
tests/__init__.py
tests/test_detector.py
projectstructor-2025.5.180959.dist-info/METADATA
projectstructor-2025.5.180959.dist-info/WHEEL
projectstructor-2025.5.180959.dist-info/top_level.txt
projectstructor-2025.5.180959.dist-info/RECORD
