Metadata-Version: 2.4
Name: ProjectStructoR
Version: 2025.5.180959
Summary: A tool for detecting project structure and technology stack with the help of GPT.
Home-page: https://github.com/chigwell/projectstructor
Author: Eugene Evstafev
Author-email: chigwel@gmail.com
License-File: LICENSE
Requires-Dist: requests
Requires-Dist: openai
Requires-Dist: lngdetector
Requires-Dist: prettytable
Requires-Dist: python-magic
Requires-Dist: pathspec
Requires-Dist: gptintegration==0.0.3
Dynamic: author
Dynamic: author-email
Dynamic: description
Dynamic: description-content-type
Dynamic: home-page
Dynamic: license-file
Dynamic: requires-dist
Dynamic: summary
